{"v":"4.8.0","meta":{"g":"LottieFiles AE 3.4.5","a":"","k":"","d":"","tc":"#F8F7F3"},"fr":60,"ip":0,"op":106,"w":10000,"h":10000,"nm":"Hex Elements","ddd":0,"assets":[],"layers":[{"ddd":0,"ind":7,"ty":3,"nm":"Null 1","sr":1,"ks":{"o":{"a":0,"k":0,"ix":11},"r":{"a":0,"k":0,"ix":10},"p":{"a":0,"k":[5000,5000,0],"ix":2},"a":{"a":0,"k":[0,0,0],"ix":1},"s":{"a":0,"k":[85,85,100],"ix":6}},"ao":0,"ip":0,"op":300,"st":0,"bm":0},{"ddd":0,"ind":12,"ty":4,"nm":"Shape Layer 1","parent":7,"sr":1,"ks":{"o":{"a":1,"k":[{"i":{"x":[0.5],"y":[1]},"o":{"x":[0.5],"y":[0]},"t":105,"s":[100]},{"t":150,"s":[0]}],"ix":11},"r":{"a":0,"k":0,"ix":10},"p":{"a":0,"k":[0,0,0],"ix":2},"a":{"a":0,"k":[-264,-328,0],"ix":1},"s":{"a":0,"k":[815.299,815.299,100],"ix":6}},"ao":0,"shapes":[{"ty":"gr","it":[{"ty":"sr","sy":2,"d":1,"pt":{"a":0,"k":6,"ix":3},"p":{"a":0,"k":[0,0],"ix":4},"r":{"a":0,"k":0,"ix":5},"or":{"a":1,"k":[{"i":{"x":[0.5],"y":[1]},"o":{"x":[0.5],"y":[0]},"t":105,"s":[650]},{"t":180,"s":[1450]}],"ix":7},"os":{"a":0,"k":0,"ix":9},"ix":1,"nm":"Polystar Path 1","mn":"ADBE Vector Shape - Star","hd":false},{"ty":"rd","nm":"Round Corners 1","r":{"a":0,"k":0,"ix":1},"ix":2,"mn":"ADBE Vector Filter - RC","hd":false},{"ty":"st","c":{"a":0,"k":[0.878431379795,0.678431391716,0.145098045468,1],"ix":3},"o":{"a":0,"k":100,"ix":4},"w":{"a":1,"k":[{"i":{"x":[0.833],"y":[1]},"o":{"x":[0.167],"y":[0]},"t":41.125,"s":[30]},{"i":{"x":[0.5],"y":[1]},"o":{"x":[0.5],"y":[0]},"t":105,"s":[10]},{"t":180,"s":[0]}],"ix":5},"lc":2,"lj":1,"ml":4,"bm":0,"nm":"Stroke 1","mn":"ADBE Vector Graphic - Stroke","hd":false},{"ty":"tr","p":{"a":0,"k":[-264,-328],"ix":2},"a":{"a":0,"k":[0,0],"ix":1},"s":{"a":0,"k":[100,100],"ix":3},"r":{"a":0,"k":89.63,"ix":6},"o":{"a":0,"k":100,"ix":7},"sk":{"a":0,"k":0,"ix":4},"sa":{"a":0,"k":0,"ix":5},"nm":"Transform"}],"nm":"Polystar 1","np":4,"cix":2,"bm":0,"ix":1,"mn":"ADBE Vector Group","hd":false},{"ty":"tm","s":{"a":0,"k":0,"ix":1},"e":{"a":1,"k":[{"i":{"x":[0.25],"y":[1]},"o":{"x":[0.33],"y":[0]},"t":0,"s":[0]},{"t":105,"s":[100]}],"ix":2},"o":{"a":1,"k":[{"i":{"x":[0.25],"y":[1]},"o":{"x":[0.33],"y":[0]},"t":0,"s":[0]},{"t":105,"s":[72]}],"ix":3},"m":1,"ix":2,"nm":"Trim Paths 1","mn":"ADBE Vector Filter - Trim","hd":false}],"ip":0,"op":300,"st":0,"bm":0}],"markers":[]}